dw/__init__.py
dw/__init___spec.py
python_dw-0.6.1.dist-info/LICENSE
python_dw-0.6.1.dist-info/METADATA
python_dw-0.6.1.dist-info/WHEEL
python_dw-0.6.1.dist-info/entry_points.txt
python_dw-0.6.1.dist-info/top_level.txt
python_dw-0.6.1.dist-info/RECORD
