Metadata-Version: 2.1
Name: python-dw
Version: 0.6.1
Summary: Data Wrangler (dw)
Home-page: https://github.com/MountainField/dw
Author: Takahide Nogayama
Author-email: nogayama@gmail.com
Project-URL: Bug Tracker, https://github.com/MountainField/dw/issues
Classifier: Programming Language :: Python :: 3
Classifier: License :: OSI Approved :: MIT License
Classifier: Operating System :: OS Independent
Requires-Python: >=3.6
License-File: LICENSE
Requires-Dist: openpyxl
Provides-Extra: dev
Requires-Dist: uspec ; extra == 'dev'
Requires-Dist: PyHamcrest ; extra == 'dev'
Requires-Dist: yapf ; extra == 'dev'
Provides-Extra: test
Requires-Dist: uspec ; extra == 'test'
Requires-Dist: PyHamcrest ; extra == 'test'
